enumagic/__init__.py
enumagic/_iter.py
enumagic/_mapping.py
enumagic/_str.py
enumagic/py.typed
enumagic-0.2.0.dist-info/LICENSE.rst
enumagic-0.2.0.dist-info/METADATA
enumagic-0.2.0.dist-info/WHEEL
enumagic-0.2.0.dist-info/top_level.txt
enumagic-0.2.0.dist-info/RECORD
