Metadata-Version: 2.1
Name: enumagic
Version: 0.2.0
Summary: Enums infused with magic.
Home-page: https://github.com/ObserverOfTime/enumagic.py
Author: ObserverOfTime
Author-email: chronobserver@disroot.org
License: Zlib
Project-URL: Bug tracker, https://github.com/ObserverOfTime/enumagic.py/issues
Project-URL: Donations, https://github.com/sponsors/ObserverOfTime
Keywords: enum,magic
Classifier: Development Status :: 4 - Beta
Classifier: Intended Audience :: Developers
Classifier: License :: OSI Approved :: zlib/libpng License
Classifier: Natural Language :: English
Classifier: Operating System :: OS Independent
Classifier: Programming Language :: Python
Classifier: Programming Language :: Python :: 3
Classifier: Programming Language :: Python :: 3.7
Classifier: Programming Language :: Python :: 3.8
Classifier: Programming Language :: Python :: 3.9
Classifier: Programming Language :: Python :: 3.10
Classifier: Programming Language :: Python :: 3 :: Only
Classifier: Topic :: Software Development :: Libraries :: Python Modules
Classifier: Typing :: Typed
Requires-Python: >=3.7
License-File: LICENSE.rst
Provides-Extra: dev
Requires-Dist: sphinx (~=5.1.1) ; extra == 'dev'
Requires-Dist: sphinx-rtd-theme (~=1.0) ; extra == 'dev'
